README.rst
setup.py
hmPy.egg-info/PKG-INFO
hmPy.egg-info/SOURCES.txt
hmPy.egg-info/dependency_links.txt
hmPy.egg-info/requires.txt
hmPy.egg-info/top_level.txt
hmpy/__init__.py
hmpy/interface.py
hmpy/layout.py
hmpy/window.py
hmpy/util/__init__.py
hmpy/util/color.py
hmpy/util/timer.py
hmpy/views/__init__.py
hmpy/views/button.py
hmpy/views/chart.py
hmpy/views/dial.py
hmpy/views/gauge.py
hmpy/views/lcd.py
hmpy/views/led.py
hmpy/views/progress_bar.py
hmpy/views/slider.py
hmpy/views/switch.py
hmpy/views/view.py