Metadata-Version: 1.0
Name: hmPy
Version: 0.2.0
Summary: A python library for generating human machine interfaces
Home-page: https://github.com/PyLC/hmPy
Author: UNKNOWN
Author-email: UNKNOWN
License: GPL v3
Platform: UNKNOWN
